fundi_scopegen/__init__.py
fundi_scopegen/build.py
fundi_scopegen/cli.py
fundi_scopegen/flatenize.py
fundi_scopegen/py.typed
fundi_scopegen/resolve.py
fundi_scopegen/util.py
fundi_scopegen-0.0.1.dist-info/METADATA
fundi_scopegen-0.0.1.dist-info/WHEEL
fundi_scopegen-0.0.1.dist-info/entry_points.txt
fundi_scopegen-0.0.1.dist-info/RECORD
