Metadata-Version: 2.4
Name: fundi-scopegen
Version: 0.0.1
Summary: Generate scope type that can be used to safely inject values using FunDIs scope values resolution
Author-email: kuyugama <mail.kuyugama@gmail.com>
Requires-Python: >=3.10
Requires-Dist: fundi>=1.2.2
Requires-Dist: typer>=0.16.0
